pentiumprox/__init__.py
pentiumprox-0.0.1.dist-info/METADATA
pentiumprox-0.0.1.dist-info/WHEEL
pentiumprox-0.0.1.dist-info/top_level.txt
pentiumprox-0.0.1.dist-info/RECORD
