Metadata-Version: 2.1
Name: pentiumprox
Version: 0.0.1
Summary: Library for programs
Author: Anonymous
Author-email: <mohammedfaisal3366@gmail.com>
Keywords: python,programs
Classifier: Programming Language :: Python :: 3
Classifier: Operating System :: Unix
Classifier: Operating System :: MacOS :: MacOS X
Classifier: Operating System :: Microsoft :: Windows
